<?xml version="1.0" encoding="UTF-8"?>
<users xmlns="http://www.demandware.com/xml/impex/user/2007-09-05">
    <user login="volodymyr.lysenko@osf-commerce.com" enabled-flag="true">
        <credentials>
            <external-id>8b092a0f-90aa-43c5-808c-0ae37e41da59</external-id>
        </credentials>
        <profile>
            <first-name>Volodymyr</first-name>
            <last-name>Lysenko</last-name>
            <email>volodymyr.lysenko@osf-commerce.com</email>
        </profile>
    </user>

    <user login="balinisteanuoanadenisa@gmail.com" enabled-flag="true">
        <credentials>
            <external-id>de336690-84e6-4db8-ae38-be6fb178b1cb</external-id>
        </credentials>
        <profile>
            <first-name>Denisa</first-name>
            <last-name>Balinisteanu</last-name>
            <email>balinisteanuoanadenisa@gmail.com</email>
            <preferred-data-locale>none</preferred-data-locale>
        </profile>
    </user>

</users>
